quantgo/__init__.py
quantgodata-1.0.1.dist-info/METADATA
quantgodata-1.0.1.dist-info/WHEEL
quantgodata-1.0.1.dist-info/top_level.txt
quantgodata-1.0.1.dist-info/RECORD
