Metadata-Version: 2.4
Name: quantgoData
Version: 1.0.1
Summary: QuantGo SDK - Tushare兼容的量化数据接口
Home-page: https://quantgo.ai
Author: QuantGo Team
Author-email: QuantGo Team <support@quantgo.ai>
License: MIT
Project-URL: Homepage, https://quantgo.ai
Keywords: quantgo,tushare,stock,data,api,quant
Classifier: Development Status :: 4 - Beta
Classifier: Intended Audience :: Developers
Classifier: License :: OSI Approved :: MIT License
Classifier: Programming Language :: Python :: 3
Requires-Python: >=3.7
Requires-Dist: requests>=2.25.0
Requires-Dist: pandas>=1.3.0
Dynamic: author
Dynamic: home-page
Dynamic: requires-python
